setgraphviz/__init__.py
setgraphviz/examples.py
setgraphviz/setgraphviz.py
setgraphviz-1.0.3.dist-info/licenses/LICENSE
setgraphviz-1.0.3.dist-info/METADATA
setgraphviz-1.0.3.dist-info/WHEEL
setgraphviz-1.0.3.dist-info/top_level.txt
setgraphviz-1.0.3.dist-info/RECORD
