Metadata-Version: 2.4
Name: setgraphviz
Version: 1.0.3
Summary: setgraphviz is a Python library to automatically set the system paths to graphviz.
Author-email: Erdogan Taskesen <erdogant@gmail.com>
License: MIT License
Project-URL: Homepage, https://erdogant.github.io/setgraphviz
Project-URL: Download, https://github.com/erdogant/setgraphviz/archive/{version}.tar.gz
Keywords: Python,
Classifier: Programming Language :: Python :: 3
Classifier: License :: OSI Approved :: MIT License
Classifier: Operating System :: OS Independent
Requires-Python: >=3
License-File: LICENSE
Requires-Dist: requests
Dynamic: license-file
